{"facets" : {"org_facet" : [{"count" : 4 , "term" : "EUROPEAN UNION"} , {"count" : 4 , "term" : "WORLD TRADE ORGANIZATION"} , {"count" : 2 , "term" : "ARCHER DANIELS MIDLAND CO"} , {"count" : 2 , "term" : "BARNEY'S INC"} , {"count" : 2 , "term" : "ISETAN CO"} , {"count" : 2 , "term" : "JAPAN AIRLINES"} , {"count" : 2 , "term" : "MOTOROLA INC"} , {"count" : 2 , "term" : "SUMITOMO CORP"} , {"count" : 1 , "term" : "311"} , {"count" : 1 , "term" : "AJINOMOTO CO"} , {"count" : 1 , "term" : "ALL NIPPON AIRWAYS"} , {"count" : 1 , "term" : "ALPHA THERAPEUTIC CORP"} , {"count" : 1 , "term" : "ANNALS OF IMPROBABLE RESEARCH"} , {"count" : 1 , "term" : "ANR COAL"} , {"count" : 1 , "term" : "APPLE COMPUTER INC"}]} , "offset" : "0" , "results" : [] , "tokens" : ["japan" , "publication_year:[1996]" , "publication_month:[10]"] , "total" : 192}