{"facets" : {"org_facet" : [{"count" : 7 , "term" : "INTERNATIONAL MONETARY FUND"} , {"count" : 5 , "term" : "WORLD BANK"} , {"count" : 4 , "term" : "GENERAL MOTORS CORP"} , {"count" : 4 , "term" : "SONY CORP"} , {"count" : 4 , "term" : "UNITED NATIONS"} , {"count" : 3 , "term" : "EUROPEAN UNION"} , {"count" : 3 , "term" : "FORD MOTOR CO"} , {"count" : 3 , "term" : "RENAULT SA"} , {"count" : 3 , "term" : "SECURITY COUNCIL"} , {"count" : 3 , "term" : "TOYOTA MOTOR CORP"} , {"count" : 2 , "term" : "DAIMLERCHRYSLER AG"} , {"count" : 2 , "term" : "NEW YORK YANKEES"} , {"count" : 2 , "term" : "NISSAN MOTOR COMPANY LIMITED"} , {"count" : 2 , "term" : "ROYAL DUTCH\/SHELL GROUP"} , {"count" : 1 , "term" : "ABC INC"}]} , "offset" : "0" , "results" : [] , "tokens" : ["japan" , "publication_year:[2006]" , "publication_month:[09]"] , "total" : 166}